punctuator/LICENSE
punctuator/__init__.py
punctuator/api.py
punctuator/example_input.txt
punctuator/main.py
punctuator/models.py
punctuator/path_config.json
punctuator_lvl9_inga-1.1.29.dist-info/METADATA
punctuator_lvl9_inga-1.1.29.dist-info/WHEEL
punctuator_lvl9_inga-1.1.29.dist-info/entry_points.txt
punctuator_lvl9_inga-1.1.29.dist-info/top_level.txt
punctuator_lvl9_inga-1.1.29.dist-info/RECORD
