Metadata-Version: 2.1
Name: punctuator-lvl9-inga
Version: 1.1.29
Summary: A frontend to punctuation prediction for Icelandic text
Home-page: https://github.com/cadia-lvl/punctuation-prediction/tree/master/punctuation_package
Author: Helga Svala Sigurðardóttir
Author-email: helgas@ru.is
License: MIT
Platform: UNKNOWN
Classifier: Environment :: GPU :: NVIDIA CUDA :: 10.2
Classifier: Intended Audience :: Developers
Classifier: Intended Audience :: Science/Research
Classifier: License :: OSI Approved :: MIT License
Classifier: Programming Language :: Python :: 3.7
Classifier: Topic :: Utilities
Classifier: Topic :: Text Processing :: Linguistic
Requires-Python: >=3.7.*
Requires-Dist: tensorflow (>=2.1.0)
Requires-Dist: torch (>=1.4.0)
Requires-Dist: transformers (>=2.11.0)
